YehuoStm32KuKaifaShizhanZhinan/README.md
YehuoStm32KuKaifaShizhanZhinan/__init__.py
YehuoStm32KuKaifaShizhanZhinan/__main__.py
YehuoStm32KuKaifaShizhanZhinan/file.epub
YehuoStm32KuKaifaShizhanZhinan/index.html
YehuoStm32KuKaifaShizhanZhinan/css/__init__.py
YehuoStm32KuKaifaShizhanZhinan/css/annotations.css
YehuoStm32KuKaifaShizhanZhinan/css/main.css
YehuoStm32KuKaifaShizhanZhinan/css/normalize.css
YehuoStm32KuKaifaShizhanZhinan/css/popup.css
YehuoStm32KuKaifaShizhanZhinan/font/__init__.py
YehuoStm32KuKaifaShizhanZhinan/font/fontello.eot
YehuoStm32KuKaifaShizhanZhinan/font/fontello.svg
YehuoStm32KuKaifaShizhanZhinan/font/fontello.ttf
YehuoStm32KuKaifaShizhanZhinan/font/fontello.woff
YehuoStm32KuKaifaShizhanZhinan/img/__init__.py
YehuoStm32KuKaifaShizhanZhinan/img/annotator-glyph-sprite.png
YehuoStm32KuKaifaShizhanZhinan/img/annotator-icon-sprite.png
YehuoStm32KuKaifaShizhanZhinan/img/apple-touch-icon.png
YehuoStm32KuKaifaShizhanZhinan/img/cancelfullscreen.png
YehuoStm32KuKaifaShizhanZhinan/img/close.png
YehuoStm32KuKaifaShizhanZhinan/img/fullscreen.png
YehuoStm32KuKaifaShizhanZhinan/img/loader.gif
YehuoStm32KuKaifaShizhanZhinan/img/menu-icon.png
YehuoStm32KuKaifaShizhanZhinan/img/save.png
YehuoStm32KuKaifaShizhanZhinan/img/saved.png
YehuoStm32KuKaifaShizhanZhinan/img/settings-s.png
YehuoStm32KuKaifaShizhanZhinan/img/settings.png
YehuoStm32KuKaifaShizhanZhinan/img/star.png
YehuoStm32KuKaifaShizhanZhinan/js/__init__.py
YehuoStm32KuKaifaShizhanZhinan/js/epub.js
YehuoStm32KuKaifaShizhanZhinan/js/epub.min.js
YehuoStm32KuKaifaShizhanZhinan/js/epub.min.map
YehuoStm32KuKaifaShizhanZhinan/js/hooks.min.js
YehuoStm32KuKaifaShizhanZhinan/js/hooks.min.map
YehuoStm32KuKaifaShizhanZhinan/js/reader.js
YehuoStm32KuKaifaShizhanZhinan/js/reader.js.map
YehuoStm32KuKaifaShizhanZhinan/js/reader.min.js
YehuoStm32KuKaifaShizhanZhinan/js/reader.min.map
YehuoStm32KuKaifaShizhanZhinan/js/hooks/__init__.py
YehuoStm32KuKaifaShizhanZhinan/js/hooks/extensions/__init__.py
yehuo_stm32_ku_kaifa_shizhan_zhinan-2024.3.5.0.dist-info/METADATA
yehuo_stm32_ku_kaifa_shizhan_zhinan-2024.3.5.0.dist-info/WHEEL
yehuo_stm32_ku_kaifa_shizhan_zhinan-2024.3.5.0.dist-info/entry_points.txt
yehuo_stm32_ku_kaifa_shizhan_zhinan-2024.3.5.0.dist-info/top_level.txt
yehuo_stm32_ku_kaifa_shizhan_zhinan-2024.3.5.0.dist-info/RECORD
